{"chunk_definitions":[{"chunk_id":"csetup_chunk","chunk_label":"setup","document_id":"60A90DFF","expansion_state":0,"options":{"echo":false,"engine":"r","include":false,"label":"setup","message":false,"warning":false},"row":18,"row_count":1,"visible":true},{"chunk_id":"ctobn4kvaj0r8","chunk_label":"unnamed-chunk-1","document_id":"60A90DFF","expansion_state":0,"options":{"engine":"r","label":"unnamed-chunk-122"},"row":59,"row_count":1,"visible":true},{"chunk_id":"c77xvkyb2192h","chunk_label":"unnamed-chunk-2","document_id":"60A90DFF","expansion_state":0,"options":{"engine":"r","label":"unnamed-chunk-123"},"row":148,"row_count":1,"visible":true},{"chunk_id":"caqxmgwuft589","chunk_label":"unnamed-chunk-3","document_id":"60A90DFF","expansion_state":0,"options":{"engine":"r","label":"unnamed-chunk-147"},"row":157,"row_count":1,"visible":true},{"chunk_id":"cjb1rt6tviycd","chunk_label":"unnamed-chunk-4","document_id":"60A90DFF","expansion_state":0,"options":{"engine":"r","label":"unnamed-chunk-146"},"row":163,"row_count":1,"visible":true},{"chunk_id":"chs3czifl23dp","chunk_label":"unnamed-chunk-5","document_id":"60A90DFF","expansion_state":0,"options":{"engine":"r","label":"unnamed-chunk-140"},"row":168,"row_count":1,"visible":true},{"chunk_id":"ce9vdp7tnfdpg","chunk_label":"unnamed-chunk-6","document_id":"60A90DFF","expansion_state":0,"options":{"engine":"r","label":"unnamed-chunk-137"},"row":177,"row_count":1,"visible":true},{"chunk_id":"cxy15gaif28cz","chunk_label":"unnamed-chunk-7","document_id":"60A90DFF","expansion_state":0,"options":{"engine":"r","label":"unnamed-chunk-142"},"row":183,"row_count":1,"visible":true},{"chunk_id":"cehic7bhujz36","chunk_label":"unnamed-chunk-8","document_id":"60A90DFF","expansion_state":0,"options":{"engine":"r","label":"unnamed-chunk-143"},"row":189,"row_count":1,"visible":true}],"chunk_rendered_width":700,"default_chunk_options":{"autodep":true,"cache":true,"error":false},"doc_write_time":1592969331,"working_dir":null}